sotopia/__init__.py
sotopia/logging.py
sotopia/py.typed
sotopia/server.py
sotopia/utils.py
sotopia/agents/__init__.py
sotopia/agents/base_agent.py
sotopia/agents/generate_agent_background.py
sotopia/agents/llm_agent.py
sotopia/agents/redis_agent.py
sotopia/api/README.md
sotopia/api/__init__.py
sotopia/api/fastapi_server.py
sotopia/api/websocket_utils.py
sotopia/cli/__init__.py
sotopia/cli/app.py
sotopia/cli/benchmark/__init__.py
sotopia/cli/benchmark/benchmark.py
sotopia/cli/install/__init__.py
sotopia/cli/install/install.py
sotopia/cli/install/menu.py
sotopia/cli/install/published_datasets.json
sotopia/cli/rich_pixels/__init__.py
sotopia/cli/rich_pixels/_pixel.py
sotopia/database/__init__.py
sotopia/database/aggregate_annotations.py
sotopia/database/annotators.py
sotopia/database/auto_expires_mixin.py
sotopia/database/base_models.py
sotopia/database/env_agent_combo_storage.py
sotopia/database/evaluation_dimensions.py
sotopia/database/handshake.py
sotopia/database/logs.py
sotopia/database/persistent_profile.py
sotopia/database/serialization.py
sotopia/database/session_transaction.py
sotopia/database/storage_backend.py
sotopia/database/waiting_room.py
sotopia/envs/__init__.py
sotopia/envs/evaluators.py
sotopia/envs/parallel.py
sotopia/experimental/__init__.py
sotopia/experimental/server.py
sotopia/experimental/agents/base_agent.py
sotopia/experimental/agents/datamodels.py
sotopia/experimental/agents/evaluators.py
sotopia/experimental/agents/logs.py
sotopia/experimental/agents/moderator.py
sotopia/experimental/agents/redis_agent.py
sotopia/experimental/envs/__init__.py
sotopia/experimental/envs/generate_executable.py
sotopia/experimental/envs/templates/multiagents.jinja2
sotopia/experimental/envs/utility_nodes/chat_print_node.py
sotopia/generation_utils/__init__.py
sotopia/generation_utils/generate.py
sotopia/generation_utils/output_parsers.py
sotopia/messages/__init__.py
sotopia/messages/message_classes.py
sotopia/messages/messenger.py
sotopia/renderers/__init__.py
sotopia-0.1.5.dist-info/METADATA
sotopia-0.1.5.dist-info/WHEEL
sotopia-0.1.5.dist-info/entry_points.txt
sotopia-0.1.5.dist-info/licenses/LICENSE
sotopia-0.1.5.dist-info/RECORD
