Metadata-Version: 2.4
Name: sotopia
Version: 0.1.5
Summary: A platform for simulating and evaluating social interaction.
Author-email: Hao Zhu <prokilchu@gmail.com>, Xuhui Zhou <xuhuiz@cs.cmu.edu>
License: MIT License
License-File: LICENSE
Requires-Python: <3.13,>=3.10
Requires-Dist: aact
Requires-Dist: absl-py<3.0.0,>=2.0.0
Requires-Dist: gin-config<0.6.0,>=0.5.0
Requires-Dist: hiredis>=3.0.0
Requires-Dist: json-repair<0.49.0,>=0.35.0
Requires-Dist: litellm>=1.65.0
Requires-Dist: lxml<6.0.0,>=4.9.3
Requires-Dist: openai<2.0.0,>=1.11.0
Requires-Dist: pettingzoo==1.25.0
Requires-Dist: pydantic<3.0.0,>=2.5.0
Requires-Dist: redis-om<0.4.0,>=0.3.0
Requires-Dist: rich<15.0.0,>=13.6.0
Requires-Dist: together<1.5.0,>=0.2.4
Provides-Extra: anthropic
Requires-Dist: anthropic; extra == 'anthropic'
Provides-Extra: api
Requires-Dist: fastapi[standard]; extra == 'api'
Requires-Dist: modal; extra == 'api'
Requires-Dist: streamlit; extra == 'api'
Requires-Dist: uvicorn; extra == 'api'
Provides-Extra: cohere
Requires-Dist: cohere; extra == 'cohere'
Provides-Extra: examples
Requires-Dist: datasets; extra == 'examples'
Requires-Dist: pandas; extra == 'examples'
Requires-Dist: scipy; extra == 'examples'
Requires-Dist: torch; extra == 'examples'
Requires-Dist: transformers; extra == 'examples'
Provides-Extra: google-generativeai
Requires-Dist: google-generativeai; extra == 'google-generativeai'
Provides-Extra: groq
Requires-Dist: groq; extra == 'groq'
Provides-Extra: test
Requires-Dist: pytest; extra == 'test'
Requires-Dist: pytest-asyncio; extra == 'test'
Requires-Dist: pytest-cov; extra == 'test'
